LLMagic/__init__.py
LLMagic/base/__init__.py
LLMagic/base/base.py
LLMagic/llms/__init__.py
LLMagic/llms/Mixtral/__init__.py
LLMagic/llms/Mixtral/mixtral.py
LLMagic/llms/Mixtral/utils.py
LLMagic-0.0.4.dist-info/METADATA
LLMagic-0.0.4.dist-info/WHEEL
LLMagic-0.0.4.dist-info/top_level.txt
LLMagic-0.0.4.dist-info/RECORD
