Metadata-Version: 2.1
Name: LLMagic
Version: 0.0.4
Summary: LLMagic: A Python toolkit for building Large Language Model (LLM) apps with efficient wrappers. Simplify NLP development with battle-tested reliability for production environments. Unleash the power of LLMs effortlessly. Get started now!
Home-page: https://github.com/Soumadip-Saha/LLMagic
Author: Soumadip Saha
Author-email: soumadipsaha2000@gmail.com
Classifier: Development Status :: 3 - Alpha
Classifier: Intended Audience :: Developers
Classifier: Topic :: Software Development :: Build Tools
Classifier: License :: OSI Approved :: MIT License
Classifier: Programming Language :: Python :: 3.8
Classifier: Programming Language :: Python :: 3.9
Classifier: Programming Language :: Python :: 3.10
Classifier: Programming Language :: Python :: 3.11
Classifier: Programming Language :: Python :: 3 :: Only
